autodistill_seggpt/__init__.py
autodistill_seggpt/colors.py
autodistill_seggpt/combinadics.py
autodistill_seggpt/dataset_utils.py
autodistill_seggpt/few_shot_ontology.py
autodistill_seggpt/find_best_examples.py
autodistill_seggpt/metrics.py
autodistill_seggpt/postprocessing.py
autodistill_seggpt/sam_refine.py
autodistill_seggpt/seggpt.py
autodistill_seggpt/train.py
autodistill_seggpt/training.py
autodistill_seggpt/find_examples/__init__.py
autodistill_seggpt/find_examples/common.py
autodistill_seggpt/find_examples/greedy.py
autodistill_seggpt/find_examples/sample.py
autodistill_seggpt/find_examples/sample_old.py
autodistill_seggpt-0.1.6.dist-info/METADATA
autodistill_seggpt-0.1.6.dist-info/WHEEL
autodistill_seggpt-0.1.6.dist-info/top_level.txt
autodistill_seggpt-0.1.6.dist-info/RECORD
