Metadata-Version: 2.1
Name: autodistill-seggpt
Version: 0.1.6
Summary: SegGPT for use with Autodistill
Home-page: https://github.com/autodistill/autodistill-seggpt
Author: andrew-healey
Author-email: andrew@roboflow.com
Classifier: Programming Language :: Python :: 3
Classifier: License :: OSI Approved :: MIT License
Classifier: Operating System :: OS Independent
Requires-Python: >=3.7
Requires-Dist: torch
Requires-Dist: autodistill
Requires-Dist: numpy (>=1.20.0)
Requires-Dist: opencv-python (>=4.6.0)
Requires-Dist: rf-segment-anything
Requires-Dist: supervision (>=0.12.0)
Requires-Dist: pycocotools
Requires-Dist: timm
Requires-Dist: fairscale
Requires-Dist: detectron2-layers
Requires-Dist: combinadics
Provides-Extra: dev
Requires-Dist: flake8 ; extra == 'dev'
Requires-Dist: black (==22.3.0) ; extra == 'dev'
Requires-Dist: isort ; extra == 'dev'
Requires-Dist: twine ; extra == 'dev'
Requires-Dist: pytest ; extra == 'dev'
Requires-Dist: wheel ; extra == 'dev'
